odoo/addons/sale_blanket_order/README.rst
odoo/addons/sale_blanket_order/__init__.py
odoo/addons/sale_blanket_order/__manifest__.py
odoo/addons/sale_blanket_order/data/ir_cron.xml
odoo/addons/sale_blanket_order/data/sequence.xml
odoo/addons/sale_blanket_order/i18n/de.po
odoo/addons/sale_blanket_order/i18n/es.po
odoo/addons/sale_blanket_order/i18n/fr.po
odoo/addons/sale_blanket_order/i18n/fr_FR.po
odoo/addons/sale_blanket_order/i18n/it.po
odoo/addons/sale_blanket_order/i18n/pt.po
odoo/addons/sale_blanket_order/i18n/sale_blanket_order.pot
odoo/addons/sale_blanket_order/models/__init__.py
odoo/addons/sale_blanket_order/models/blanket_orders.py
odoo/addons/sale_blanket_order/models/sale_config_settings.py
odoo/addons/sale_blanket_order/models/sale_orders.py
odoo/addons/sale_blanket_order/readme/CONTEXT.md
odoo/addons/sale_blanket_order/readme/CONTRIBUTORS.md
odoo/addons/sale_blanket_order/readme/CREDITS.md
odoo/addons/sale_blanket_order/readme/DESCRIPTION.md
odoo/addons/sale_blanket_order/readme/ROADMAP.md
odoo/addons/sale_blanket_order/readme/USAGE.md
odoo/addons/sale_blanket_order/report/report.xml
odoo/addons/sale_blanket_order/report/templates.xml
odoo/addons/sale_blanket_order/security/ir.model.access.csv
odoo/addons/sale_blanket_order/security/security.xml
odoo/addons/sale_blanket_order/static/description/BO_actions.png
odoo/addons/sale_blanket_order/static/description/BO_form.png
odoo/addons/sale_blanket_order/static/description/BO_lines.png
odoo/addons/sale_blanket_order/static/description/BO_menu.png
odoo/addons/sale_blanket_order/static/description/PO_BOLine.png
odoo/addons/sale_blanket_order/static/description/PO_from_BO.png
odoo/addons/sale_blanket_order/static/description/icon.png
odoo/addons/sale_blanket_order/static/description/index.html
odoo/addons/sale_blanket_order/static/src/js/disable_add_order_line.esm.js
odoo/addons/sale_blanket_order/tests/__init__.py
odoo/addons/sale_blanket_order/tests/test_blanket_orders.py
odoo_addon_sale_blanket_order-18.0.1.2.1.dist-info/METADATA
odoo_addon_sale_blanket_order-18.0.1.2.1.dist-info/WHEEL
odoo_addon_sale_blanket_order-18.0.1.2.1.dist-info/top_level.txt
odoo_addon_sale_blanket_order-18.0.1.2.1.dist-info/RECORD
