Metadata-Version: 2.1
Name: odoo-addon-sale_blanket_order
Version: 18.0.1.2.1
Requires-Python: >=3.10
Requires-Dist: odoo==18.0.*
Summary: Blanket Orders
Home-page: https://github.com/OCA/sale-blanket
License: AGPL-3
Author: Acsone SA/NV, Odoo Community Association (OCA)
Author-email: support@odoo-community.org
Classifier: Programming Language :: Python
Classifier: Framework :: Odoo
Classifier: Framework :: Odoo :: 18.0
Classifier: License :: OSI Approved :: GNU Affero General Public License v3
